exiffind
