Metadata-Version: 1.1
Name: exiffind
Version: 0.0.5
Summary: Find images by their exif tags
Home-page: https://github.com/k0rmarun/exiffind
Author: Kormarun
Author-email: kormarun@gmail.com
License: MIT
Platform: UNKNOWN
Classifier: Development Status :: 4 - Beta
Classifier: Environment :: Console
Classifier: Intended Audience :: End Users/Desktop
Classifier: Topic :: Desktop Environment :: File Managers
Classifier: Topic :: Multimedia :: Graphics
Classifier: Topic :: Utilities
Classifier: License :: OSI Approved :: MIT License
Classifier: Programming Language :: Python :: 3
Classifier: Programming Language :: Python :: 3.3
Classifier: Programming Language :: Python :: 3.4
Classifier: Programming Language :: Python :: 3.5
